buz/__init__.py
buz/command/__init__.py
buz/command/asynchronous/__init__.py
buz/command/asynchronous/base_command_handler.py
buz/command/asynchronous/command_bus.py
buz/command/asynchronous/command_handler.py
buz/command/asynchronous/middleware/__init__.py
buz/command/asynchronous/middleware/base_handle_middleware.py
buz/command/asynchronous/middleware/handle_middleware.py
buz/command/asynchronous/middleware/handle_middleware_chain_resolver.py
buz/command/asynchronous/self_process/__init__.py
buz/command/asynchronous/self_process/self_process_command_bus.py
buz/command/command.py
buz/command/more_than_one_command_handler_related_exception.py
buz/command/synchronous/__init__.py
buz/command/synchronous/base_command_handler.py
buz/command/synchronous/command_bus.py
buz/command/synchronous/command_handler.py
buz/command/synchronous/middleware/__init__.py
buz/command/synchronous/middleware/base_handle_middleware.py
buz/command/synchronous/middleware/handle_middleware.py
buz/command/synchronous/middleware/handle_middleware_chain_resolver.py
buz/command/synchronous/self_process/__init__.py
buz/command/synchronous/self_process/self_process_command_bus.py
buz/command/synchronous/synced_async/__init__.py
buz/command/synchronous/synced_async/synced_async_command_bus.py
buz/event/__init__.py
buz/event/async_consumer.py
buz/event/async_event_bus.py
buz/event/async_event_bus_with_publish_result.py
buz/event/async_subscriber.py
buz/event/async_worker.py
buz/event/base_async_subscriber.py
buz/event/base_subscriber.py
buz/event/consumer.py
buz/event/dead_letter_queue/__init__.py
buz/event/dead_letter_queue/dlq_criteria.py
buz/event/dead_letter_queue/dlq_record.py
buz/event/dead_letter_queue/dlq_repository.py
buz/event/event.py
buz/event/event_bus.py
buz/event/event_bus_publish_result.py
buz/event/exceptions/__init__.py
buz/event/exceptions/event_not_published_exception.py
buz/event/exceptions/event_restore_exception.py
buz/event/exceptions/subscribers_not_found_exception.py
buz-2.26.0.dist-info/LICENSE
buz-2.26.0.dist-info/METADATA
buz-2.26.0.dist-info/WHEEL
buz-2.26.0.dist-info/RECORD
